yt_dlp_transcripts/__init__.py
yt_dlp_transcripts/__main__.py
yt_dlp_transcripts/core.py
yt_dlp_transcripts-0.1.1.dist-info/LICENSE
yt_dlp_transcripts-0.1.1.dist-info/METADATA
yt_dlp_transcripts-0.1.1.dist-info/WHEEL
yt_dlp_transcripts-0.1.1.dist-info/entry_points.txt
yt_dlp_transcripts-0.1.1.dist-info/RECORD
