Metadata-Version: 2.1
Name: yt-dlp-transcripts
Version: 0.1.1
Summary: Extract video information and transcripts from YouTube videos, playlists, and channels
Home-page: https://linuxiscool.xyz
License: MIT
Keywords: youtube,transcripts,yt-dlp,video,download,metadata,playlist,channel
Author: Shawn Anderson
Author-email: shawn@longtailfinancial.com
Requires-Python: >=3.9,<4.0
Classifier: Development Status :: 4 - Beta
Classifier: Intended Audience :: Developers
Classifier: Intended Audience :: Science/Research
Classifier: License :: OSI Approved :: MIT License
Classifier: Programming Language :: Python :: 3
Classifier: Programming Language :: Python :: 3.9
Classifier: Programming Language :: Python :: 3.10
Classifier: Programming Language :: Python :: 3.11
Classifier: Programming Language :: Python :: 3.12
Classifier: Programming Language :: Python :: 3.7
Classifier: Programming Language :: Python :: 3.8
Classifier: Topic :: Multimedia :: Video
Classifier: Topic :: Software Development :: Libraries :: Python Modules
Requires-Dist: click (>=8.0.0)
Requires-Dist: youtube-transcript-api (>=0.6.0)
Requires-Dist: yt-dlp (>=2024.1.0)
Project-URL: Documentation, https://github.com/LinuxIsCool/yt-dlp-transcripts#readme
Project-URL: Repository, https://github.com/LinuxIsCool/yt-dlp-transcripts
